kim/__init__.py
kim/exception.py
kim/field.py
kim/mapper.py
kim/role.py
kim/utils.py
kim/pipelines/__init__.py
kim/pipelines/base.py
kim/pipelines/boolean.py
kim/pipelines/collection.py
kim/pipelines/datetime.py
kim/pipelines/marshaling.py
kim/pipelines/nested.py
kim/pipelines/numeric.py
kim/pipelines/serialization.py
kim/pipelines/static.py
kim/pipelines/string.py
py_kim-1.1.0.dist-info/DESCRIPTION.rst
py_kim-1.1.0.dist-info/METADATA
py_kim-1.1.0.dist-info/RECORD
py_kim-1.1.0.dist-info/WHEEL
py_kim-1.1.0.dist-info/metadata.json
py_kim-1.1.0.dist-info/top_level.txt
tests/test_pipelines/__init__.py
tests/test_pipelines/test_base.py
tests/test_pipelines/test_boolean.py
tests/test_pipelines/test_collection.py
tests/test_pipelines/test_datetime.py
tests/test_pipelines/test_nested.py
tests/test_pipelines/test_numeric.py
tests/test_pipelines/test_static.py
tests/test_pipelines/test_string.py
