Metadata-Version: 2.0
Name: py-kim
Version: 1.1.0
Summary: Kim: A JSON Serialization and Marshaling framework
Home-page: https://github.com/mikeywaites/kim
Author: Mikey Waites, Jack Saunders
Author-email: mike@oldstlabs.com
License: MIT License
Download-URL: https://github.com/mikeywaites/kim/releases/tag/1.1.0
Platform: UNKNOWN
Classifier: Development Status :: 5 - Production/Stable
Classifier: Intended Audience :: Developers
Classifier: Natural Language :: English
Classifier: License :: OSI Approved :: MIT License
Classifier: Programming Language :: Python
Classifier: Programming Language :: Python :: 2.6
Classifier: Programming Language :: Python :: 2.7
Classifier: Programming Language :: Python :: 3
Classifier: Programming Language :: Python :: 3.3
Classifier: Programming Language :: Python :: 3.4
Classifier: Programming Language :: Python :: 3.5
Classifier: Programming Language :: Python :: 3.6
Classifier: Programming Language :: Python :: Implementation :: CPython
Classifier: Programming Language :: Python :: Implementation :: PyPy
Requires-Dist: iso8601 (>=0.1.10)
Requires-Dist: six (>=1.9.0)
Provides-Extra: develop
Requires-Dist: Sphinx (==1.3.1); extra == 'develop'
Requires-Dist: sphinx-bootstrap-theme (==0.4.5); extra == 'develop'
Requires-Dist: tabulate (==0.7.7); extra == 'develop'
Requires-Dist: pytest (==2.8); extra == 'develop'
Requires-Dist: pytest-cov (==1.8.1); extra == 'develop'
Requires-Dist: pytest-spec (==0.2.24); extra == 'develop'
Requires-Dist: sqlalchemy (==1.0.4); extra == 'develop'
Requires-Dist: mock (==1.3.0); extra == 'develop'
Requires-Dist: ipdb; extra == 'develop'
